simple_mamba/__init__.py
simple_mamba/main.py
simple_mamba/ssm.py
simple_mamba/two.py
simple_mamba-0.0.4.dist-info/LICENSE
simple_mamba-0.0.4.dist-info/WHEEL
simple_mamba-0.0.4.dist-info/METADATA
simple_mamba-0.0.4.dist-info/RECORD
